python_hologram_api/__init__.py
python_hologram_api/cellular.py
python_hologram_api/client.py
python_hologram_api/cloud_messaging.py
python_hologram_api/constants.py
python_hologram_api/data_plans.py
python_hologram_api/device_tags.py
python_hologram_api/devices.py
python_hologram_api/organization.py
python_hologram_api/spacebridge.py
python_hologram_api/user.py
python_hologram_api-0.1.6.dist-info/DESCRIPTION.rst
python_hologram_api-0.1.6.dist-info/METADATA
python_hologram_api-0.1.6.dist-info/RECORD
python_hologram_api-0.1.6.dist-info/WHEEL
python_hologram_api-0.1.6.dist-info/metadata.json
python_hologram_api-0.1.6.dist-info/top_level.txt
