Metadata-Version: 2.0
Name: python-hologram-api
Version: 0.1.6
Summary: Python client for https://dashboard.hologram.io/api.
Home-page: https://github.com/vicyap/python-hologram-api
Author: Victor Yap
Author-email: victor@vicyap.com
License: MIT license
Keywords: python_hologram_api
Platform: UNKNOWN
Classifier: Development Status :: 2 - Pre-Alpha
Classifier: Intended Audience :: Developers
Classifier: License :: OSI Approved :: MIT License
Classifier: Natural Language :: English
Classifier: Programming Language :: Python :: 2
Classifier: Programming Language :: Python :: 2.7
Classifier: Programming Language :: Python :: 3
Classifier: Programming Language :: Python :: 3.4
Classifier: Programming Language :: Python :: 3.5
Classifier: Programming Language :: Python :: 3.6
Requires-Dist: requests
